{
  "doc_id": "CBE Annual Report 2012-13_85a1691a684245c3",
  "root": {
    "title": "Document",
    "page_start": 1,
    "page_end": 20,
    "child_sections": [
      {
        "title": "Document",
        "page_start": 1,
        "page_end": 20,
        "child_sections": [],
        "key_entities": [],
        "summary": "Particulars |  |  | 2012/13 | 2011/12 |  | percent | \n |  |  |  |  |  | Change | \n | Interest Income: |  | 9,539.17 | 6,703.45 | 42.3 |  | \n | Loans and advances |  | 5,330.44 | 3,607.81 | 47.7 |  | \n | Government bonds |  | 39.12 | 27.68 | 41.3 |  | \n | Coupon and corporate bonds |  | 4,102.71 | 3,053.13 | 34.4 |  | \n | Correspondents banks | ...",
        "data_types_present": [
          "tables",
          "text"
        ]
      }
    ],
    "key_entities": [],
    "summary": "Particulars |  |  | 2012/13 | 2011/12 |  | percent | \n |  |  |  |  |  | Change | \n | Interest Income: |  | 9,539.17 | 6,703.45 | 42.3 |  | \n | Loans and advances |  | 5,330.44 | 3,607.81 | 47.7 |  | \n | Government bonds |  | 39.12 | 27.68 | 41.3 |  | \n | Coupon and corporate bonds |  | 4,102.71 | 3,053.13 | 34.4 |  | \n | Correspondents banks | ...",
    "data_types_present": []
  },
  "total_pages": 20
}